patsnap_pythonSDK/__init__.py
patsnap_pythonSDK/__main__.py
patsnap_pythonSDK/auth.py
patsnap_pythonSDK/cli.py
patsnap_pythonSDK/client.py
patsnap_pythonSDK/errors.py
patsnap_pythonSDK/http.py
patsnap_pythonSDK/models/__init__.py
patsnap_pythonSDK/models/analytics/__init__.py
patsnap_pythonSDK/models/analytics/search.py
patsnap_pythonSDK/models/search/__init__.py
patsnap_pythonSDK/models/search/patents.py
patsnap_pythonSDK/namespaces/__init__.py
patsnap_pythonSDK/namespaces/analytics.py
patsnap_pythonSDK/namespaces/patents.py
patsnap_pythonSDK/resources/__init__.py
patsnap_pythonSDK/resources/analytics/__init__.py
patsnap_pythonSDK/resources/analytics/search.py
patsnap_pythonSDK/resources/search/__init__.py
patsnap_pythonSDK/resources/search/patents.py
patsnap_pythonSDK/utils/backoff.py
patsnap_pythonSDK/utils/tracing.py
patsnap_pythonsdk-0.1.1.dist-info/licenses/LICENSE
patsnap_pythonsdk-0.1.1.dist-info/METADATA
patsnap_pythonsdk-0.1.1.dist-info/WHEEL
patsnap_pythonsdk-0.1.1.dist-info/entry_points.txt
patsnap_pythonsdk-0.1.1.dist-info/top_level.txt
patsnap_pythonsdk-0.1.1.dist-info/RECORD
