Metadata-Version: 2.4
Name: patsnap-pythonSDK
Version: 0.1.1
Summary: Unofficial Python SDK for Patsnap's patent and innovation intelligence APIs
Author-email: Frazer Kearl <fkearl@patsnap.com>
License-Expression: MIT
Project-URL: Homepage, https://github.com/zenos27/patsnap-pythonSDK
Project-URL: Bug Reports, https://github.com/zenos27/patsnap-pythonSDK/issues
Project-URL: Source, https://github.com/zenos27/patsnap-pythonSDK
Project-URL: Documentation, https://github.com/zenos27/patsnap-pythonSDK/blob/main/README.md
Keywords: patsnap,patents,api,sdk,intellectual-property,innovation
Classifier: Development Status :: 4 - Beta
Classifier: Intended Audience :: Developers
Classifier: Intended Audience :: Science/Research
Classifier: Operating System :: OS Independent
Classifier: Programming Language :: Python :: 3
Classifier: Programming Language :: Python :: 3.8
Classifier: Programming Language :: Python :: 3.9
Classifier: Programming Language :: Python :: 3.10
Classifier: Programming Language :: Python :: 3.11
Classifier: Programming Language :: Python :: 3.12
Classifier: Topic :: Scientific/Engineering
Classifier: Topic :: Software Development :: Libraries :: Python Modules
Requires-Python: >=3.8
License-File: LICENSE
Requires-Dist: requests<3,>=2.31.0
Requires-Dist: pydantic<3,>=2.6.0
Provides-Extra: dev
Requires-Dist: pytest>=7.0; extra == "dev"
Requires-Dist: pytest-cov>=4.0.0; extra == "dev"
Requires-Dist: black>=23.0.0; extra == "dev"
Requires-Dist: isort>=5.12.0; extra == "dev"
Dynamic: license-file
